energy_monitor/__init__.py
energy_monitor/__main__.py
energy_monitor/llm_usage_example.py
energy_monitor/monitor.py
python_energy_monitor-0.0.1.dist-info/LICENSE
python_energy_monitor-0.0.1.dist-info/METADATA
python_energy_monitor-0.0.1.dist-info/WHEEL
python_energy_monitor-0.0.1.dist-info/top_level.txt
python_energy_monitor-0.0.1.dist-info/RECORD
