Metadata-Version: 2.2
Name: python_energy_monitor
Version: 0.0.1
Summary: A Python package to monitor energy consumption and CO2 emissions for LLM models and other computational tasks.
Home-page: https://github.com/codemaker2015/energy_monitor
Author: Vishnu Sivan
Author-email: Vishnu Sivan <codemaker2015@gmail.com>
License: MIT License
Project-URL: Homepage, https://github.com/codemaker2015/energy_monitor
Project-URL: Issues, https://github.com/codemaker2015/energy_monitor/issues
Classifier: Programming Language :: Python :: 3
Classifier: License :: OSI Approved :: MIT License
Classifier: Operating System :: OS Independent
Requires-Python: >=3.6
License-File: LICENSE
Requires-Dist: psutil
Requires-Dist: pynvml
Requires-Dist: codecarbon
Dynamic: author
Dynamic: home-page
Dynamic: requires-python
